{
  "kind": "collectionType",
  "collectionName": "case_study_categories",
  "info": {
    "singularName": "case-study-category",
    "pluralName": "case-study-categories",
    "displayName": "Case Study Category"
  },
  "options": {
    "draftAndPublish": true
  },
  "pluginOptions": {},
  "attributes": {
    "name": {
      "type": "string",
      "required": true
    },
    "slug": {
      "type": "string",
      "required": true
    },
    "casestudy_pages": {
      "type": "relation",
      "relation": "oneToMany",
      "target": "api::casestudy-page.casestudy-page",
      "mappedBy": "categories"
    }
  }
}
